<?xml version="1.0" encoding="utf-8" ?>
<dwsync>
<file name="icon-48-archive.png" local="128931496348593750" remote="-1" testing="0" />
<file name="icon-48-article-add.png" local="128931496350000000" remote="-1" testing="0" />
<file name="icon-48-article.png" local="128931496351406250" remote="-1" testing="0" />
<file name="icon-48-category.png" local="128931496352343750" remote="-1" testing="0" />
<file name="icon-48-checkin.png" local="128931496353281250" remote="-1" testing="0" />
<file name="icon-48-component.png" local="128931496354062500" remote="-1" testing="0" />
<file name="icon-48-config.png" local="128931496355000000" remote="-1" testing="0" />
<file name="icon-48-content.png" local="128931496355781250" remote="-1" testing="0" />
<file name="icon-48-cpanel.png" local="128931496356875000" remote="-1" testing="0" />
<file name="icon-48-extension.png" local="128931496357656250" remote="-1" testing="0" />
<file name="icon-48-frontpage.png" local="128931496358593750" remote="-1" testing="0" />
<file name="icon-48-generic.png" local="128931496359531250" remote="-1" testing="0" />
<file name="icon-48-help_header.png" local="128931496361718750" remote="-1" testing="0" />
<file name="icon-48-inbox.png" local="128931496364843750" remote="-1" testing="0" />
<file name="icon-48-info.png" local="128931496366875000" remote="-1" testing="0" />
<file name="icon-48-install.png" local="128931496368437500" remote="-1" testing="0" />
<file name="icon-48-language.png" local="128931496369531250" remote="-1" testing="0" />
<file name="icon-48-massmail.png" local="128931496370312500" remote="-1" testing="0" />
<file name="icon-48-media.png" local="128931496371093750" remote="-1" testing="0" />
<file name="icon-48-menu.png" local="128931496372031250" remote="-1" testing="0" />
<file name="icon-48-menumgr.png" local="128931496372968750" remote="-1" testing="0" />
<file name="icon-48-module.png" local="128931496373593750" remote="-1" testing="0" />
<file name="icon-48-plugin.png" local="128931496374687500" remote="-1" testing="0" />
<file name="icon-48-section.png" local="128931496375625000" remote="-1" testing="0" />
<file name="icon-48-static.png" local="128931496376406250" remote="-1" testing="0" />
<file name="icon-48-stats.png" local="128931496377500000" remote="-1" testing="0" />
<file name="icon-48-themes.png" local="128931496379375000" remote="-1" testing="0" />
<file name="icon-48-trash.png" local="128931496380468750" remote="-1" testing="0" />
<file name="icon-48-user.png" local="128931496381406250" remote="-1" testing="0" />
<file name="news1.png" local="128931496382500000" remote="-1" testing="0" />
<file name="news2.png" local="128931496383750000" remote="-1" testing="0" />
</dwsync>